NetkillerFreebsd/README.md
NetkillerFreebsd/__init__.py
NetkillerFreebsd/__main__.py
NetkillerFreebsd/file.epub
NetkillerFreebsd/index.html
NetkillerFreebsd/css/__init__.py
NetkillerFreebsd/css/annotations.css
NetkillerFreebsd/css/main.css
NetkillerFreebsd/css/normalize.css
NetkillerFreebsd/css/popup.css
NetkillerFreebsd/font/__init__.py
NetkillerFreebsd/font/fontello.eot
NetkillerFreebsd/font/fontello.svg
NetkillerFreebsd/font/fontello.ttf
NetkillerFreebsd/font/fontello.woff
NetkillerFreebsd/img/__init__.py
NetkillerFreebsd/img/annotator-glyph-sprite.png
NetkillerFreebsd/img/annotator-icon-sprite.png
NetkillerFreebsd/img/apple-touch-icon.png
NetkillerFreebsd/img/cancelfullscreen.png
NetkillerFreebsd/img/close.png
NetkillerFreebsd/img/fullscreen.png
NetkillerFreebsd/img/loader.gif
NetkillerFreebsd/img/menu-icon.png
NetkillerFreebsd/img/save.png
NetkillerFreebsd/img/saved.png
NetkillerFreebsd/img/settings-s.png
NetkillerFreebsd/img/settings.png
NetkillerFreebsd/img/star.png
NetkillerFreebsd/js/__init__.py
NetkillerFreebsd/js/epub.js
NetkillerFreebsd/js/epub.min.js
NetkillerFreebsd/js/epub.min.map
NetkillerFreebsd/js/hooks.min.js
NetkillerFreebsd/js/hooks.min.map
NetkillerFreebsd/js/reader.js
NetkillerFreebsd/js/reader.js.map
NetkillerFreebsd/js/reader.min.js
NetkillerFreebsd/js/reader.min.map
NetkillerFreebsd/js/hooks/__init__.py
NetkillerFreebsd/js/hooks/extensions/__init__.py
NetkillerFreebsd/js/hooks/extensions/highlight.js
NetkillerFreebsd/js/libs/__init__.py
NetkillerFreebsd/js/libs/jquery.min.js
NetkillerFreebsd/js/libs/localforage.min.js
NetkillerFreebsd/js/libs/screenfull.js
NetkillerFreebsd/js/libs/screenfull.min.js
NetkillerFreebsd/js/libs/zip.min.js
NetkillerFreebsd/js/plugins/__init__.py
NetkillerFreebsd/js/plugins/hypothesis.js
NetkillerFreebsd/js/plugins/search.js
netkiller_freebsd-2024.3.5.0.dist-info/METADATA
netkiller_freebsd-2024.3.5.0.dist-info/WHEEL
netkiller_freebsd-2024.3.5.0.dist-info/entry_points.txt
netkiller_freebsd-2024.3.5.0.dist-info/top_level.txt
netkiller_freebsd-2024.3.5.0.dist-info/RECORD
